{
  "type": "FeatureCollection",
  "features": [
    {
      "type": "Feature",
      "geometry": {
        "type": "Point",
        "coordinates": [2.3522, 48.8566, 50]
      },
      "properties": {
        "name": "Bâtiment A",
        "consumption": "120 kWh",
        "type": "Résidentiel",
        "year": 1990,
        "height": 50
      }
    },
    {
      "type": "Feature",
      "geometry": {
        "type": "Point",
        "coordinates": [2.3417, 48.8575, 70]
      },
      "properties": {
        "name": "Bâtiment B",
        "consumption": "200 kWh",
        "type": "Commercial",
        "year": 2005,
        "height": 70
      }
    }
  ]
}